{
    "20": [
        {
            "name": "Абрамова Наталья Сергеевна",
            "vrn": 4304003517311,
            "birthdate": "27.04.1978 00:00:00",
            "party": "КПРФ",
            "smart_vote": 1
        },
        {
            "name": "Щепихин Михаил Борисович",
            "vrn": 4304003517503,
            "birthdate": "20.11.1958 00:00:00",
            "party": "ЕР",
            "smart_vote": 0
        },
        {
            "name": "Шишниашвили Гурам Важаевич",
            "vrn": 4304003517125,
            "birthdate": "22.07.1985 00:00:00",
            "party": "ЛДПР",
            "smart_vote": 0
        },
        {
            "name": "Гламаздин Антон Анатольевич",
            "vrn": 4304003517625,
            "birthdate": "25.06.1980 00:00:00",
            "party": "СР",
            "smart_vote": 0
        }
    ],
    "25": [
        {
            "name": "Абуев Айнур Альбертович",
            "vrn": 4304003517397,
            "birthdate": "05.12.2001 00:00:00",
            "party": "КПРФ",
            "smart_vote": 0
        },
        {
            "name": "Генералов Сергей Вячеславович",
            "vrn": 4304003517251,
            "birthdate": "04.01.1975 00:00:00",
            "party": "ЕР",
            "smart_vote": 0
        },
        {
            "name": "Арефьев Николай Валерьевич",
            "vrn": 4304003517184,
            "birthdate": "27.12.1992 00:00:00",
            "party": "ЛДПР",
            "smart_vote": 0
        },
        {
            "name": "Календр Александр Давидович",
            "vrn": 4304003517601,
            "birthdate": "03.05.1971 00:00:00",
            "party": "СР",
            "smart_vote": 1
        },
        {
            "name": "Ижерская Евгения Александровна",
            "vrn": 4304003516875,
            "birthdate": "13.06.1987 00:00:00",
            "party": "РОДИНА",
            "smart_vote": 0
        }
    ],
    "22": [
        {
            "name": "Агаларов Заур Аскерович",
            "vrn": 4304003517425,
            "birthdate": "23.04.1982 00:00:00",
            "party": "КПРФ",
            "smart_vote": 1
        },
        {
            "name": "Белов Александр Владимирович",
            "vrn": 4304003517694,
            "birthdate": "01.01.1978 00:00:00",
            "party": "ЕР",
            "smart_vote": 0
        },
        {
            "name": "Джунусова Эльвира Алпысбаевна",
            "vrn": 4304003517098,
            "birthdate": "12.12.1985 00:00:00",
            "party": "ЛДПР",
            "smart_vote": 0
        }
    ],
    "8": [
        {
            "name": "Аитов Халит Андреевич",
            "vrn": 4304001351184,
            "birthdate": "13.02.1987 00:00:00",
            "party": "КПРФ",
            "smart_vote": 1
        },
        {
            "name": "Тарханов Владимир Саввич",
            "vrn": 4304001351286,
            "birthdate": "24.11.1965 00:00:00",
            "party": "ЕР",
            "smart_vote": 0
        },
        {
            "name": "Калашникова Лариса Николаевна",
            "vrn": 4304001350795,
            "birthdate": "13.02.1975 00:00:00",
            "party": "ЛДПР",
            "smart_vote": 0
        }
    ],
    "34": [
        {
            "name": "Акперов Вугар Равваг оглы",
            "vrn": 4304004355998,
            "birthdate": "07.10.1973 00:00:00",
            "party": "КПРФ",
            "smart_vote": 0
        },
        {
            "name": "Ашимов Фархад Мусаевич",
            "vrn": 4304004355877,
            "birthdate": "15.12.1978 00:00:00",
            "party": "ЕР",
            "smart_vote": 0
        },
        {
            "name": "Лаптева Анна Михайловна",
            "vrn": 4304004355252,
            "birthdate": "15.01.1983 00:00:00",
            "party": "ЛДПР",
            "smart_vote": 1
        },
        {
            "name": "Нурмагомедов Буньямин Шихмагомедович",
            "vrn": 4304004355844,
            "birthdate": "02.02.1979 00:00:00",
            "party": "СР",
            "smart_vote": 0
        }
    ],
    "30": [
        {
            "name": "Афонькин Данила Владимирович",
            "vrn": 4304004356136,
            "birthdate": "23.02.1972 00:00:00",
            "party": "КПРФ",
            "smart_vote": 0
        },
        {
            "name": "Нестеров Андрей Юрьевич",
            "vrn": 4304004356177,
            "birthdate": "12.04.1983 00:00:00",
            "party": "ЕР",
            "smart_vote": 0
        },
        {
            "name": "Евсеев Олег Викторович",
            "vrn": 4304004355479,
            "birthdate": "10.04.1953 00:00:00",
            "party": "ЛДПР",
            "smart_vote": 0
        },
        {
            "name": "Чернышов Алексей Петрович",
            "vrn": 4304004356095,
            "birthdate": "21.10.1976 00:00:00",
            "party": "СР",
            "smart_vote": 1
        }
    ],
    "3": [
        {
            "name": "Ахмед Рамис Ясирович",
            "vrn": 4304001351061,
            "birthdate": "08.05.1996 00:00:00",
            "party": "КПРФ",
            "smart_vote": 0
        },
        {
            "name": "Шарапудинов Али Омарович",
            "vrn": 4304001351105,
            "birthdate": "26.11.1956 00:00:00",
            "party": "ЕР",
            "smart_vote": 0
        },
        {
            "name": "Чурилова Ольга Анатольевна",
            "vrn": 4304001350679,
            "birthdate": "13.03.1967 00:00:00",
            "party": "ЛДПР",
            "smart_vote": 0
        },
        {
            "name": "Гаджиев Рафик Забур оглы",
            "vrn": 4304001351258,
            "birthdate": "09.07.1965 00:00:00",
            "party": "СР",
            "smart_vote": 1
        }
    ],
    "27": [
        {
            "name": "Бахилин Виталий Викторович",
            "vrn": 4304003517351,
            "birthdate": "16.12.1980 00:00:00",
            "party": "КПРФ",
            "smart_vote": 1
        },
        {
            "name": "Каримов Рубин Халилевич",
            "vrn": 4304003517385,
            "birthdate": "03.07.1981 00:00:00",
            "party": "ЕР",
            "smart_vote": 0
        },
        {
            "name": "Шитова Яна Владимировна",
            "vrn": 4304003516946,
            "birthdate": "18.10.1999 00:00:00",
            "party": "ЛДПР",
            "smart_vote": 0
        },
        {
            "name": "Посявин Николай Анатольевич",
            "vrn": 4304003517531,
            "birthdate": "09.04.1977 00:00:00",
            "party": "СР",
            "smart_vote": 0
        }
    ],
    "17": [
        {
            "name": "Гайдукова Анастасия Николаевна",
            "vrn": 4304002413663,
            "birthdate": "11.02.2000 00:00:00",
            "party": "КПРФ",
            "smart_vote": 0
        },
        {
            "name": "Шабалин Игорь Юрьевич",
            "vrn": 4304002414053,
            "birthdate": "27.09.1963 00:00:00",
            "party": "ЕР",
            "smart_vote": 0
        },
        {
            "name": "Сармин Алексей Иванович",
            "vrn": 4304002413732,
            "birthdate": "22.04.1980 00:00:00",
            "party": "СР",
            "smart_vote": 1
        },
        {
            "name": "Омельченко Анастасия Дмитриевна",
            "vrn": 4304002413256,
            "birthdate": "10.06.1981 00:00:00",
            "party": "РОДИНА",
            "smart_vote": 0
        },
        {
            "name": "Богданов Николай Валерьевич",
            "vrn": 4304002413229,
            "birthdate": "24.05.1968 00:00:00",
            "party": "-",
            "smart_vote": 0
        }
    ],
    "6": [
        {
            "name": "Дунин Антон Андреевич",
            "vrn": 4304001351133,
            "birthdate": "22.07.1986 00:00:00",
            "party": "КПРФ",
            "smart_vote": 0
        },
        {
            "name": "Тихонов Александр Иванович",
            "vrn": 4304001351461,
            "birthdate": "30.12.1986 00:00:00",
            "party": "ЕР",
            "smart_vote": 0
        },
        {
            "name": "Агапов Александр Витальевич",
            "vrn": 4304001350699,
            "birthdate": "06.09.1972 00:00:00",
            "party": "ЛДПР",
            "smart_vote": 1
        },
        {
            "name": "Дорофеева Анна Сергеевна",
            "vrn": 4304001351368,
            "birthdate": "14.10.1983 00:00:00",
            "party": "СР",
            "smart_vote": 0
        },
        {
            "name": "Гюлишанова Лиана Анатольевна",
            "vrn": 4304001350594,
            "birthdate": "31.01.1970 00:00:00",
            "party": "РОДИНА",
            "smart_vote": 0
        },
        {
            "name": "Дорофеева Ирина Евгеньевна",
            "vrn": 4304001350934,
            "birthdate": "05.11.1968 00:00:00",
            "party": "-",
            "smart_vote": 0
        }
    ],
    "9": [
        {
            "name": "Дусабалиев Сабир Нарсултанович",
            "vrn": 4304002413871,
            "birthdate": "25.08.1970 00:00:00",
            "party": "КПРФ",
            "smart_vote": 0
        },
        {
            "name": "Бабаев Артур Шарафудинович",
            "vrn": 4304002413803,
            "birthdate": "09.11.1983 00:00:00",
            "party": "ЕР",
            "smart_vote": 0
        },
        {
            "name": "Гордиенко Николай Владимирович",
            "vrn": 4304002413498,
            "birthdate": "07.05.1992 00:00:00",
            "party": "ЛДПР",
            "smart_vote": 0
        },
        {
            "name": "Коноваленко Владимир Александрович",
            "vrn": 4304002413686,
            "birthdate": "02.06.1974 00:00:00",
            "party": "СР",
            "smart_vote": 1
        }
    ],
    "32": [
        {
            "name": "Ельчанинов Алексей Владимирович",
            "vrn": 4304004355970,
            "birthdate": "14.05.1992 00:00:00",
            "party": "КПРФ",
            "smart_vote": 0
        },
        {
            "name": "Седов Игорь Юрьевич",
            "vrn": 4304004356054,
            "birthdate": "31.05.1967 00:00:00",
            "party": "ЕР",
            "smart_vote": 0
        },
        {
            "name": "Кокин Александр Александрович",
            "vrn": 4304004355141,
            "birthdate": "30.05.1984 00:00:00",
            "party": "ЛДПР",
            "smart_vote": 0
        },
        {
            "name": "Шпорин Олег Витальевич",
            "vrn": 4304004356603,
            "birthdate": "22.07.1985 00:00:00",
            "party": "СР",
            "smart_vote": 1
        }
    ],
    "14": [
        {
            "name": "Завгороднева Оксана Валерьевна",
            "vrn": 4304002413822,
            "birthdate": "23.02.1979 00:00:00",
            "party": "КПРФ",
            "smart_vote": 0
        },
        {
            "name": "Тарасенко Виктор Станиславович",
            "vrn": 4304002414855,
            "birthdate": "16.07.1988 00:00:00",
            "party": "ЕР",
            "smart_vote": 0
        },
        {
            "name": "Тарасенко Андрей Олегович",
            "vrn": 4304002413564,
            "birthdate": "13.09.1996 00:00:00",
            "party": "ЛДПР",
            "smart_vote": 0
        },
        {
            "name": "Сарайкин Владимир Игоревич",
            "vrn": 4304002413977,
            "birthdate": "14.05.1971 00:00:00",
            "party": "СР",
            "smart_vote": 1
        }
    ],
    "10": [
        {
            "name": "Ирканалиев Наиль Канапиевич",
            "vrn": 4304002413651,
            "birthdate": "30.10.1993 00:00:00",
            "party": "КПРФ",
            "smart_vote": 0
        },
        {
            "name": "Якоркин Александр Викторович",
            "vrn": 4304002413792,
            "birthdate": "19.06.1997 00:00:00",
            "party": "ЕР",
            "smart_vote": 0
        },
        {
            "name": "Куантыров Булат Мухаетдинович",
            "vrn": 4304002413545,
            "birthdate": "14.12.1982 00:00:00",
            "party": "ЛДПР",
            "smart_vote": 0
        },
        {
            "name": "Дивинчук Олег Валентинович",
            "vrn": 4304002413674,
            "birthdate": "27.08.1970 00:00:00",
            "party": "СР",
            "smart_vote": 1
        },
        {
            "name": "Очир-Горяев Цэрен Николаевич",
            "vrn": 4304002413284,
            "birthdate": "06.10.1986 00:00:00",
            "party": "РОДИНА",
            "smart_vote": 0
        },
        {
            "name": "Васильева Ольга Владимировна",
            "vrn": 4304002412681,
            "birthdate": "26.12.1954 00:00:00",
            "party": "-",
            "smart_vote": 0
        }
    ],
    "35": [
        {
            "name": "Коняев Владислав Гарриевич",
            "vrn": 4304004356012,
            "birthdate": "17.07.1977 00:00:00",
            "party": "КПРФ",
            "smart_vote": 1
        },
        {
            "name": "Абельдаев Айвар Русланович",
            "vrn": 4304004356204,
            "birthdate": "30.07.1983 00:00:00",
            "party": "ЕР",
            "smart_vote": 0
        },
        {
            "name": "Джунусов Аслан Нариманович",
            "vrn": 4304004355155,
            "birthdate": "12.11.1978 00:00:00",
            "party": "ЛДПР",
            "smart_vote": 0
        }
    ],
    "7": [
        {
            "name": "Куликов Олег Викторович",
            "vrn": 4304001351147,
            "birthdate": "08.02.1967 00:00:00",
            "party": "КПРФ",
            "smart_vote": 0
        },
        {
            "name": "Горбунов Тимур Александрович",
            "vrn": 4304001351340,
            "birthdate": "13.02.1984 00:00:00",
            "party": "ЕР",
            "smart_vote": 0
        },
        {
            "name": "Шевченко Михаил Николаевич",
            "vrn": 4304001351326,
            "birthdate": "11.10.1983 00:00:00",
            "party": "СР",
            "smart_vote": 1
        },
        {
            "name": "Булыгин Андрей Павлович",
            "vrn": 4304001347040,
            "birthdate": "26.10.1977 00:00:00",
            "party": "-",
            "smart_vote": 0
        }
    ],
    "13": [
        {
            "name": "Кунавин Никита Валерьевич",
            "vrn": 4304002413895,
            "birthdate": "04.06.1986 00:00:00",
            "party": "КПРФ",
            "smart_vote": 1
        },
        {
            "name": "Крылов Геннадий Федорович",
            "vrn": 4304002413961,
            "birthdate": "28.01.1949 00:00:00",
            "party": "ЕР",
            "smart_vote": 0
        },
        {
            "name": "Туктаров Фархад Рубиндарович",
            "vrn": 4304002413157,
            "birthdate": "05.02.1975 00:00:00",
            "party": "-",
            "smart_vote": 0
        }
    ],
    "19": [
        {
            "name": "Маношкин Михаил Михайлович",
            "vrn": 4304003517411,
            "birthdate": "17.11.1951 00:00:00",
            "party": "КПРФ",
            "smart_vote": 0
        },
        {
            "name": "Витковский Артур Ярославович",
            "vrn": 4304003517287,
            "birthdate": "27.06.1974 00:00:00",
            "party": "ЕР",
            "smart_vote": 0
        },
        {
            "name": "Рулин Олег Николаевич",
            "vrn": 4304003518749,
            "birthdate": "29.05.1990 00:00:00",
            "party": "ЛДПР",
            "smart_vote": 0
        },
        {
            "name": "Полякова Марина Николаевна",
            "vrn": 4304003517653,
            "birthdate": "12.07.1987 00:00:00",
            "party": "СР",
            "smart_vote": 1
        },
        {
            "name": "Денисов Артем Юрьевич",
            "vrn": 4304003516187,
            "birthdate": "09.07.1995 00:00:00",
            "party": "-",
            "smart_vote": 0
        }
    ],
    "21": [
        {
            "name": "Мартынов Александр Геннадьевич",
            "vrn": 4304003517517,
            "birthdate": "27.10.1979 00:00:00",
            "party": "КПРФ",
            "smart_vote": 0
        },
        {
            "name": "Асанова Жанна Тастанбековна",
            "vrn": 4304003517263,
            "birthdate": "28.01.1982 00:00:00",
            "party": "ЕР",
            "smart_vote": 0
        },
        {
            "name": "Гаврилов Сергей Юрьевич",
            "vrn": 4304003517084,
            "birthdate": "24.07.1978 00:00:00",
            "party": "ЛДПР",
            "smart_vote": 1
        },
        {
            "name": "Чекунов Алексей Сергеевич",
            "vrn": 4304003517568,
            "birthdate": "29.06.1993 00:00:00",
            "party": "СР",
            "smart_vote": 0
        },
        {
            "name": "Гаврилов Александр Николаевич",
            "vrn": 4304003517030,
            "birthdate": "08.05.1983 00:00:00",
            "party": "-",
            "smart_vote": 0
        }
    ],
    "1": [
        {
            "name": "Медведев Александр Юрьевич",
            "vrn": 4304001351119,
            "birthdate": "18.06.1987 00:00:00",
            "party": "КПРФ",
            "smart_vote": 0
        },
        {
            "name": "Чернякова Валентина Владимировна",
            "vrn": 4304001351161,
            "birthdate": "28.12.1979 00:00:00",
            "party": "ЕР",
            "smart_vote": 0
        },
        {
            "name": "Почевалова Татьяна Ивановна",
            "vrn": 4304001350968,
            "birthdate": "07.08.1984 00:00:00",
            "party": "ЛДПР",
            "smart_vote": 0
        },
        {
            "name": "Евдокимов Александр Анатольевич",
            "vrn": 4304001351241,
            "birthdate": "28.10.1985 00:00:00",
            "party": "СР",
            "smart_vote": 1
        }
    ],
    "26": [
        {
            "name": "Медведев Валерий Вячеславович",
            "vrn": 4304003517441,
            "birthdate": "20.05.1980 00:00:00",
            "party": "КПРФ",
            "smart_vote": 1
        },
        {
            "name": "Чагин Алексей Валерьевич",
            "vrn": 4304003517365,
            "birthdate": "01.04.1981 00:00:00",
            "party": "ЕР",
            "smart_vote": 0
        },
        {
            "name": "Кондрашов Сергей Станиславович",
            "vrn": 4304003517453,
            "birthdate": "03.06.1966 00:00:00",
            "party": "ЛДПР",
            "smart_vote": 0
        },
        {
            "name": "Булатов Дамир Каберович",
            "vrn": 4304003517545,
            "birthdate": "05.01.1967 00:00:00",
            "party": "СР",
            "smart_vote": 0
        }
    ],
    "12": [
        {
            "name": "Музлаев Александр Сергеевич",
            "vrn": 4304002413721,
            "birthdate": "21.03.1980 00:00:00",
            "party": "КПРФ",
            "smart_vote": 0
        },
        {
            "name": "Апостолов Евгений Вадимович",
            "vrn": 4304002413938,
            "birthdate": "08.10.1982 00:00:00",
            "party": "ЕР",
            "smart_vote": 0
        },
        {
            "name": "Кленов Иван Викторович",
            "vrn": 4304002413594,
            "birthdate": "13.04.1989 00:00:00",
            "party": "ЛДПР",
            "smart_vote": 0
        },
        {
            "name": "Гаврилина Любовь Николаевна",
            "vrn": 4304002413697,
            "birthdate": "06.08.1954 00:00:00",
            "party": "СР",
            "smart_vote": 1
        },
        {
            "name": "Соловьёв Юрий Михайлович",
            "vrn": 4304002413349,
            "birthdate": "31.07.1984 00:00:00",
            "party": "-",
            "smart_vote": 0
        }
    ],
    "29": [
        {
            "name": "Осипов Андрей Павлович",
            "vrn": 4304004355941,
            "birthdate": "29.09.1983 00:00:00",
            "party": "КПРФ",
            "smart_vote": 0
        },
        {
            "name": "Смирнова Камила Николаевна",
            "vrn": 4304004356109,
            "birthdate": "02.07.1988 00:00:00",
            "party": "ЕР",
            "smart_vote": 0
        },
        {
            "name": "Сяснев Виктор Александрович",
            "vrn": 4304004355175,
            "birthdate": "18.05.1995 00:00:00",
            "party": "ЛДПР",
            "smart_vote": 1
        },
        {
            "name": "Петров Сергей Геннадьевич",
            "vrn": 4304004355684,
            "birthdate": "16.03.2002 00:00:00",
            "party": "Яблоко",
            "smart_vote": 0
        },
        {
            "name": "Булло Антон Анатольевич",
            "vrn": 4304004356252,
            "birthdate": "12.05.1987 00:00:00",
            "party": "СР",
            "smart_vote": 0
        },
        {
            "name": "Бажан Артем Игоревич",
            "vrn": 4304004355047,
            "birthdate": "05.08.1972 00:00:00",
            "party": "-",
            "smart_vote": 0
        }
    ],
    "11": [
        {
            "name": "Репин Илья Николаевич",
            "vrn": 4304002413859,
            "birthdate": "05.12.1985 00:00:00",
            "party": "КПРФ",
            "smart_vote": 1
        },
        {
            "name": "Григорьев Василий Васильевич",
            "vrn": 4304002413709,
            "birthdate": "18.08.1962 00:00:00",
            "party": "ЕР",
            "smart_vote": 0
        },
        {
            "name": "Медведев Иван Викторович",
            "vrn": 4304002413533,
            "birthdate": "13.02.1995 00:00:00",
            "party": "ЛДПР",
            "smart_vote": 0
        },
        {
            "name": "Гришин Сергей Викторович",
            "vrn": 4304002413847,
            "birthdate": "25.05.1986 00:00:00",
            "party": "СР",
            "smart_vote": 0
        }
    ],
    "36": [
        {
            "name": "Ржечицкий Роман Валерьевич",
            "vrn": 4304004356036,
            "birthdate": "15.11.1979 00:00:00",
            "party": "КПРФ",
            "smart_vote": 1
        },
        {
            "name": "Симеонова Елена Ивановна",
            "vrn": 4304004356163,
            "birthdate": "20.06.1959 00:00:00",
            "party": "ЕР",
            "smart_vote": 0
        },
        {
            "name": "Перехожев Александр Леонидович",
            "vrn": 4304004355217,
            "birthdate": "09.01.1962 00:00:00",
            "party": "ЛДПР",
            "smart_vote": 0
        },
        {
            "name": "Алимуллаев Ранис Рамильевич",
            "vrn": 4304004355927,
            "birthdate": "11.03.1996 00:00:00",
            "party": "СР",
            "smart_vote": 0
        },
        {
            "name": "Заикина Ирина Александровна",
            "vrn": 4304004354625,
            "birthdate": "27.08.1973 00:00:00",
            "party": "-",
            "smart_vote": 0
        },
        {
            "name": "Мажитов Талгат Шамилевич",
            "vrn": 4304004354851,
            "birthdate": "30.01.1992 00:00:00",
            "party": "-",
            "smart_vote": 0
        }
    ],
    "2": [
        {
            "name": "Свищев Михаил Иванович",
            "vrn": 4304001351045,
            "birthdate": "23.05.1955 00:00:00",
            "party": "КПРФ",
            "smart_vote": 0
        },
        {
            "name": "Михеев Матвей Викторович",
            "vrn": 4304001351312,
            "birthdate": "16.06.1980 00:00:00",
            "party": "ЕР",
            "smart_vote": 0
        },
        {
            "name": "Кириллов Петр Юрьевич",
            "vrn": 4304001352054,
            "birthdate": "22.09.1984 00:00:00",
            "party": "ЛДПР",
            "smart_vote": 1
        },
        {
            "name": "Зариньш Эйжена Борисовна",
            "vrn": 4304001351354,
            "birthdate": "19.05.1981 00:00:00",
            "party": "СР",
            "smart_vote": 0
        },
        {
            "name": "Житерев Илья Германович",
            "vrn": 4304001347581,
            "birthdate": "27.01.1958 00:00:00",
            "party": "-",
            "smart_vote": 0
        }
    ],
    "5": [
        {
            "name": "Сердюкова Татьяна Васильевна",
            "vrn": 4304001351032,
            "birthdate": "05.01.1985 00:00:00",
            "party": "КПРФ",
            "smart_vote": 0
        },
        {
            "name": "Ермолаева Елизавета Владимировна",
            "vrn": 4304001352245,
            "birthdate": "03.10.1981 00:00:00",
            "party": "ЕР",
            "smart_vote": 0
        },
        {
            "name": "Свирин Дмитрий Викторович",
            "vrn": 4304001350781,
            "birthdate": "14.04.1979 00:00:00",
            "party": "ЛДПР",
            "smart_vote": 0
        },
        {
            "name": "Кудрявцев Сергей Сергеевич",
            "vrn": 4304001351271,
            "birthdate": "01.02.1983 00:00:00",
            "party": "СР",
            "smart_vote": 1
        },
        {
            "name": "Родихин Владимир Владимирович",
            "vrn": 4304001350612,
            "birthdate": "14.12.1982 00:00:00",
            "party": "РОДИНА",
            "smart_vote": 0
        },
        {
            "name": "Лихобабин Константин Викторович",
            "vrn": 4304001350407,
            "birthdate": "18.07.1978 00:00:00",
            "party": "-",
            "smart_vote": 0
        }
    ],
    "31": [
        {
            "name": "Смирнов Андрей Михайлович",
            "vrn": 4304004355955,
            "birthdate": "09.10.1996 00:00:00",
            "party": "КПРФ",
            "smart_vote": 1
        },
        {
            "name": "Иванова Лилия Александровна",
            "vrn": 4304004356067,
            "birthdate": "15.07.1988 00:00:00",
            "party": "ЕР",
            "smart_vote": 0
        },
        {
            "name": "Прошунина Татьяна Сергеевна",
            "vrn": 4304004355703,
            "birthdate": "26.07.1986 00:00:00",
            "party": "ЛДПР",
            "smart_vote": 0
        },
        {
            "name": "Чабак Владимир Андреевич",
            "vrn": 4304004354505,
            "birthdate": "07.04.1993 00:00:00",
            "party": "-",
            "smart_vote": 0
        }
    ],
    "15": [
        {
            "name": "Сурхаев Руслан Абдулкагирович",
            "vrn": 4304002413883,
            "birthdate": "06.07.1974 00:00:00",
            "party": "КПРФ",
            "smart_vote": 0
        },
        {
            "name": "Лимонов Владимир Михайлович",
            "vrn": 4304002413950,
            "birthdate": "22.06.1980 00:00:00",
            "party": "ЕР",
            "smart_vote": 0
        },
        {
            "name": "Шеин Сергей Михайлович",
            "vrn": 4304002413340,
            "birthdate": "18.05.1985 00:00:00",
            "party": "ЛДПР",
            "smart_vote": 0
        },
        {
            "name": "Давыдов Антон Алексеевич",
            "vrn": 4304002413768,
            "birthdate": "07.12.1986 00:00:00",
            "party": "СР",
            "smart_vote": 1
        }
    ],
    "24": [
        {
            "name": "Хисамов Динар Гусманович",
            "vrn": 4304003517478,
            "birthdate": "26.12.1980 00:00:00",
            "party": "КПРФ",
            "smart_vote": 1
        },
        {
            "name": "Кожевников Денис Александрович",
            "vrn": 4304003517490,
            "birthdate": "08.04.1989 00:00:00",
            "party": "ЕР",
            "smart_vote": 0
        },
        {
            "name": "Сущева Валерия Константиновна",
            "vrn": 4304003516977,
            "birthdate": "18.10.1999 00:00:00",
            "party": "ЛДПР",
            "smart_vote": 0
        },
        {
            "name": "Курьянов Дмитрий Валерьевич",
            "vrn": 4304003517668,
            "birthdate": "24.07.1984 00:00:00",
            "party": "СР",
            "smart_vote": 0
        },
        {
            "name": "Репин Виктор Геннадьевич",
            "vrn": 4304003516993,
            "birthdate": "30.04.1984 00:00:00",
            "party": "-",
            "smart_vote": 0
        }
    ],
    "4": [
        {
            "name": "Шарипов Ринат Руминович",
            "vrn": 4304001351075,
            "birthdate": "08.09.1973 00:00:00",
            "party": "КПРФ",
            "smart_vote": 0
        },
        {
            "name": "Джаркенов Ахмет Файзуллаевич",
            "vrn": 4304001351198,
            "birthdate": "15.09.1956 00:00:00",
            "party": "ЕР",
            "smart_vote": 0
        },
        {
            "name": "Павлов Иван Валерьевич",
            "vrn": 4304001352098,
            "birthdate": "25.07.1987 00:00:00",
            "party": "ЛДПР",
            "smart_vote": 0
        },
        {
            "name": "Адельшинов Наиль Вагизович",
            "vrn": 4304001351447,
            "birthdate": "28.10.1984 00:00:00",
            "party": "СР",
            "smart_vote": 1
        },
        {
            "name": "Сатубалдиев Анвар Жуламанович",
            "vrn": 4304001350925,
            "birthdate": "07.09.1981 00:00:00",
            "party": "-",
            "smart_vote": 0
        },
        {
            "name": "Удочкина Ксения Николаевна",
            "vrn": 4304001350914,
            "birthdate": "05.09.1983 00:00:00",
            "party": "-",
            "smart_vote": 0
        }
    ],
    "33": [
        {
            "name": "Штоколов Сергей Геннадьевич",
            "vrn": 4304004355984,
            "birthdate": "11.11.1966 00:00:00",
            "party": "КПРФ",
            "smart_vote": 0
        },
        {
            "name": "Янборисов Равиль Рашидович",
            "vrn": 4304004356122,
            "birthdate": "09.10.1989 00:00:00",
            "party": "ЕР",
            "smart_vote": 0
        },
        {
            "name": "Носова Юлия Николаевна",
            "vrn": 4304004355782,
            "birthdate": "23.02.1986 00:00:00",
            "party": "ЛДПР",
            "smart_vote": 1
        },
        {
            "name": "Иванушкин Александр Анатольевич",
            "vrn": 4304004356081,
            "birthdate": "25.02.1989 00:00:00",
            "party": "СР",
            "smart_vote": 0
        }
    ],
    "18": [
        {
            "name": "Дарьянов Александр Юрьевич",
            "vrn": 4304002413925,
            "birthdate": "14.05.1976 00:00:00",
            "party": "ЕР",
            "smart_vote": 0
        },
        {
            "name": "Родина Ольга Сергеевна",
            "vrn": 4304002414867,
            "birthdate": "07.06.1973 00:00:00",
            "party": "ЛДПР",
            "smart_vote": 0
        },
        {
            "name": "Лиджиева Мария Викторовна",
            "vrn": 4304002413835,
            "birthdate": "06.03.1981 00:00:00",
            "party": "СР",
            "smart_vote": 1
        },
        {
            "name": "Болдырев Владимир Сергеевич",
            "vrn": 4304002413272,
            "birthdate": "19.04.1990 00:00:00",
            "party": "РОДИНА",
            "smart_vote": 0
        }
    ],
    "23": [
        {
            "name": "Зоткин Михаил Геннадиевич",
            "vrn": 4304003517335,
            "birthdate": "10.06.1973 00:00:00",
            "party": "ЕР",
            "smart_vote": 0
        },
        {
            "name": "Головачев Владимир Владимирович",
            "vrn": 4304003518727,
            "birthdate": "09.08.1963 00:00:00",
            "party": "СР",
            "smart_vote": 1
        },
        {
            "name": "Тараненко Сергей Сергеевич",
            "vrn": 4304003516346,
            "birthdate": "17.04.1984 00:00:00",
            "party": "-",
            "smart_vote": 0
        }
    ],
    "16": [
        {
            "name": "Калашников Евгений Сергеевич",
            "vrn": 4304002413780,
            "birthdate": "14.02.1975 00:00:00",
            "party": "ЕР",
            "smart_vote": 0
        },
        {
            "name": "Невлюдова Мария Юрьевна",
            "vrn": 4304002413297,
            "birthdate": "05.06.1986 00:00:00",
            "party": "ЛДПР",
            "smart_vote": 0
        },
        {
            "name": "Ворох Василий Ярославович",
            "vrn": 4304002413756,
            "birthdate": "02.01.1964 00:00:00",
            "party": "СР",
            "smart_vote": 1
        },
        {
            "name": "Иноземцева Вера Александровна",
            "vrn": 4304002411611,
            "birthdate": "14.04.1998 00:00:00",
            "party": "-",
            "smart_vote": 0
        }
    ],
    "28": [
        {
            "name": "Шайдин Николай Викторович",
            "vrn": 4304003517682,
            "birthdate": "17.05.1980 00:00:00",
            "party": "ЕР",
            "smart_vote": 0
        },
        {
            "name": "Далаев Александр Сергеевич",
            "vrn": 4304003517071,
            "birthdate": "17.08.1995 00:00:00",
            "party": "ЛДПР",
            "smart_vote": 0
        },
        {
            "name": "Федоров Виктор Федорович",
            "vrn": 4304003517556,
            "birthdate": "30.03.1984 00:00:00",
            "party": "СР",
            "smart_vote": 1
        },
        {
            "name": "Соломонов Анатолий Владимирович",
            "vrn": 4304003516482,
            "birthdate": "25.04.1985 00:00:00",
            "party": "-",
            "smart_vote": 0
        }
    ]
}