{
    "1": {
        "candidate_total": {
            "4454009446481": 787,
            "4454009446638": 3028,
            "4454009446825": 2267,
            "4454009447280": 913
        },
        "is_final": 1,
        "total_non_valid": 351,
        "total_valid": 6995
    },
    "10": {
        "candidate_total": {
            "4454001196685": 2140,
            "4454001196728": 2913,
            "4454001196754": 3874,
            "4454001196767": 5013
        },
        "is_final": 1,
        "total_non_valid": 394,
        "total_valid": 13940
    },
    "11": {
        "candidate_total": {
            "4454023243016": 1750,
            "4454023243128": 6761,
            "4454023243162": 2821,
            "4454023243449": 1343
        },
        "is_final": 1,
        "total_non_valid": 569,
        "total_valid": 12675
    },
    "12": {
        "candidate_total": {
            "4454006237362": 9277,
            "4454006237370": 1824,
            "4454006237381": 2521,
            "4454006237420": 2169
        },
        "is_final": 1,
        "total_non_valid": 562,
        "total_valid": 15791
    },
    "13": {
        "candidate_total": {
            "4454010274253": 1211,
            "4454010274340": 5730,
            "4454010274453": 5695,
            "4454010274503": 1641
        },
        "is_final": 1,
        "total_non_valid": 521,
        "total_valid": 14277
    },
    "14": {
        "candidate_total": {
            "4454005164738": 1729,
            "4454005164829": 1357,
            "4454005164876": 9630,
            "4454005164967": 3441
        },
        "is_final": 1,
        "total_non_valid": 636,
        "total_valid": 16157
    },
    "15": {
        "candidate_total": {
            "4454003260954": 2497,
            "4454003261175": 11134,
            "4454003261182": 2753,
            "4454003261247": 1733
        },
        "is_final": 1,
        "total_non_valid": 533,
        "total_valid": 18117
    },
    "16": {
        "candidate_total": {
            "4454020200546": 2409,
            "4454020200598": 3090,
            "4454020200612": 9815,
            "4454020200715": 741
        },
        "is_final": 1,
        "total_non_valid": 629,
        "total_valid": 16055
    },
    "17": {
        "candidate_total": {
            "4454008478222": 2182,
            "4454008479414": 5758,
            "4454008479515": 878,
            "4454008479522": 1832
        },
        "is_final": 1,
        "total_non_valid": 386,
        "total_valid": 10650
    },
    "2": {
        "candidate_total": {
            "4454009446719": 2497,
            "4454009446887": 963,
            "4454009446893": 1897,
            "4454009447258": 3573
        },
        "is_final": 1,
        "total_non_valid": 370,
        "total_valid": 8930
    },
    "3": {
        "candidate_total": {
            "4454027335787": 1123,
            "4454027336066": 2207,
            "4454027336133": 3533,
            "4454027336155": 1119
        },
        "is_final": 1,
        "total_non_valid": 429,
        "total_valid": 7982
    },
    "4": {
        "candidate_total": {
            "4454027336056": 2632,
            "4454027336080": 2040,
            "4454027336208": 1364,
            "4454027336215": 1225
        },
        "is_final": 1,
        "total_non_valid": 343,
        "total_valid": 7261
    },
    "5": {
        "candidate_total": {
            "4454027336094": 1654,
            "4454027336146": 1680,
            "4454027336241": 6123
        },
        "is_final": 1,
        "total_non_valid": 354,
        "total_valid": 9457
    },
    "6": {
        "candidate_total": {
            "4454009446613": 1741,
            "4454009446654": 2393,
            "4454009446880": 1492,
            "4454009447264": 686
        },
        "is_final": 1,
        "total_non_valid": 294,
        "total_valid": 6312
    },
    "7": {
        "candidate_total": {
            "4454026260577": 2165,
            "4454026260725": 1673,
            "4454026260765": 3958,
            "4454026260873": 915
        },
        "is_final": 1,
        "total_non_valid": 588,
        "total_valid": 8711
    },
    "8": {
        "candidate_total": {
            "4454021371218": 7457,
            "4454021371308": 2080,
            "4454021371314": 1807,
            "4454021371320": 1810
        },
        "is_final": 1,
        "total_non_valid": 596,
        "total_valid": 13154
    },
    "9": {
        "candidate_total": {
            "4454007229955": 1534,
            "4454007230238": 3048,
            "4454007230287": 9711,
            "4454007230299": 1186
        },
        "is_final": 1,
        "total_non_valid": 638,
        "total_valid": 15479
    }
}